aws2/__init__.py
aws2/aws.py
aws2/default.yaml
aws2/image.py
aws2/instance.py
aws2/resource.py
aws2/snapshot.py
aws2/spot.py
aws2/volume.py
aws2-0.2.7.dist-info/METADATA
aws2-0.2.7.dist-info/WHEEL
aws2-0.2.7.dist-info/licence.txt
aws2-0.2.7.dist-info/top_level.txt
aws2-0.2.7.dist-info/RECORD
