Metadata-Version: 2.1
Name: aws2
Version: 0.2.7
Summary: Automate AWS spot instances
Home-page: http://github.com/simonm3/aws2.git
Author: UNKNOWN
Author-email: UNKNOWN
License: UNKNOWN
Platform: UNKNOWN
Requires-Dist: PyYAML
Requires-Dist: boto3
Requires-Dist: fabric
Requires-Dist: pandas
Requires-Dist: pyperclip
Requires-Dist: requests
